nida/__init__.py
nida-0.1.7.dist-info/METADATA
nida-0.1.7.dist-info/WHEEL
nida-0.1.7.dist-info/top_level.txt
nida-0.1.7.dist-info/RECORD
