Metadata-Version: 2.1
Name: nida
Version: 0.1.7
Summary: A python libary to Easy fetching user information based on National ID (Tanzania)
Home-page: https://github.com/Kalebu/nida
Author: Jordan Kalebu
Author-email: isaackeinstein@gmail.com
License: MIT
Download-URL: https://github.com/Kalebu/Nida/archive/0.2.tar.gz
Keywords: nida,nida apinida python packagepython nidatanzania nida,python-tanzania
Platform: UNKNOWN
Classifier: Development Status :: 3 - Alpha
Classifier: Intended Audience :: Developers
Classifier: Topic :: Software Development :: Build Tools
Classifier: License :: OSI Approved :: MIT License
Classifier: Programming Language :: Python :: 3.6
Classifier: Programming Language :: Python :: 3.7
Classifier: Programming Language :: Python :: 3.8
Classifier: Programming Language :: Python :: 3.9
Requires-Python: >=3.6
Requires-Dist: addict
Requires-Dist: requests
